pyccmm/__init__.py
pyccmm/ccmm_handler.py
pyccmm/ccmm_metadata_handler.py
pyccmm/ccmm_models.py
pyccmm/schemas/__init__.py
pyccmm/schemas/CCMM/CCMM-model.png
pyccmm/schemas/CCMM/Czech Core Metadata Model-backup.zip
pyccmm/schemas/CCMM/README.md
pyccmm/schemas/CCMM/RELEASE_NOTES.md
pyccmm/schemas/CCMM/access-rights/schema.xsd
pyccmm/schemas/CCMM/address/schema.xsd
pyccmm/schemas/CCMM/agent/schema.xsd
pyccmm/schemas/CCMM/alternate-title/schema.xsd
pyccmm/schemas/CCMM/alternate-title-type/schema.xsd
pyccmm/schemas/CCMM/application-profile/schema.xsd
pyccmm/schemas/CCMM/checksum/schema.xsd
pyccmm/schemas/CCMM/checksum-algorithm/schema.xsd
pyccmm/schemas/CCMM/contact-details/schema.xsd
pyccmm/schemas/CCMM/cs/d19697d9-b1fe-427a-874b-0a537119a6e7.svg
pyccmm/schemas/CCMM/cs/dsv.ttl
pyccmm/schemas/CCMM/cs/index.html
pyccmm/schemas/CCMM/data-service/schema.xsd
pyccmm/schemas/CCMM/dataset/schema.xsd
pyccmm/schemas/CCMM/date-type/schema.xsd
pyccmm/schemas/CCMM/description/schema.xsd
pyccmm/schemas/CCMM/description-type/schema.xsd
pyccmm/schemas/CCMM/distribution/schema.xsd
pyccmm/schemas/CCMM/documentation/schema.xsd
pyccmm/schemas/CCMM/en/d19697d9-b1fe-427a-874b-0a537119a6e7.svg
pyccmm/schemas/CCMM/en/dsv.ttl
pyccmm/schemas/CCMM/en/index.html
pyccmm/schemas/CCMM/file/schema.xsd
pyccmm/schemas/CCMM/format/schema.xsd
pyccmm/schemas/CCMM/funding-reference/schema.xsd
pyccmm/schemas/CCMM/geometry/schema.xsd
pyccmm/schemas/CCMM/identifier/schema.xsd
pyccmm/schemas/CCMM/identifier-scheme/schema.xsd
pyccmm/schemas/CCMM/language-system/schema.xsd
pyccmm/schemas/CCMM/license-document/schema.xsd
pyccmm/schemas/CCMM/location/schema.xsd
pyccmm/schemas/CCMM/location-relation-type/schema.xsd
pyccmm/schemas/CCMM/media-type/schema.xsd
pyccmm/schemas/CCMM/metadata-record/schema.xsd
pyccmm/schemas/CCMM/organization/schema.xsd
pyccmm/schemas/CCMM/provenance-statement/schema.xsd
pyccmm/schemas/CCMM/repository/schema.xsd
pyccmm/schemas/CCMM/resource/schema.xsd
pyccmm-1.0.2.dist-info/METADATA
pyccmm-1.0.2.dist-info/WHEEL
pyccmm-1.0.2.dist-info/top_level.txt
pyccmm-1.0.2.dist-info/RECORD
