Metadata-Version: 2.4
Name: pyCCMM
Version: 1.0.2
Summary: Python implementation of CCMM (Czech Core Metadata Model) standard
Author-email: "Institute of Physics, Czech Academy of Sciences" <support@fzu.cz>
License-Expression: MIT
Project-URL: Homepage, https://github.com/roman-dvorak/pyCCMM
Project-URL: Repository, https://github.com/roman-dvorak/pyCCMM
Project-URL: Documentation, https://github.com/roman-dvorak/pyCCMM/docs
Project-URL: Issues, https://github.com/roman-dvorak/pyCCMM/issues
Classifier: Development Status :: 4 - Beta
Classifier: Intended Audience :: Developers
Classifier: Operating System :: OS Independent
Classifier: Programming Language :: Python :: 3
Classifier: Programming Language :: Python :: 3.8
Classifier: Programming Language :: Python :: 3.9
Classifier: Programming Language :: Python :: 3.10
Classifier: Programming Language :: Python :: 3.11
Classifier: Topic :: Software Development :: Libraries :: Python Modules
Classifier: Topic :: Text Processing :: Markup :: XML
Requires-Python: >=3.8
Requires-Dist: lxml>=4.6.0
Requires-Dist: typing-extensions>=4.0.0; python_version < "3.10"
Provides-Extra: dev
Requires-Dist: pytest>=6.0; extra == "dev"
Requires-Dist: pytest-cov>=2.0; extra == "dev"
Requires-Dist: black>=21.0; extra == "dev"
Requires-Dist: isort>=5.0; extra == "dev"
Requires-Dist: flake8>=3.8; extra == "dev"
